redisposted/__init__.py
redisposted/base.py
redisposted/tests/__init__.py
redisposted/tests/test_base.py
redisposted-0.1.3.dist-info/LICENSE
redisposted-0.1.3.dist-info/METADATA
redisposted-0.1.3.dist-info/WHEEL
redisposted-0.1.3.dist-info/top_level.txt
redisposted-0.1.3.dist-info/RECORD
