Metadata-Version: 2.1
Name: redisposted
Version: 0.1.3
Summary: Concrete implementation of posted for Redis
License: mit
License-File: LICENSE
Requires-Dist: posted
Requires-Dist: redis==5.0.2
Requires-Dist: i2
